{"run_id": 1767595588000, "start_time": "2026-01-05 06:46:28", "type": "walking", "distance": 2380.3, "elapsed_time": 3099.0, "records": [{"lat": 37.5315317, "lon": 122.0813696, "alt": 43.2, "hr": 92, "dist": 0.0, "speed": 0.0, "time": 0, "temp": 28, "cadence": 60}, {"lat": 37.5315375, "lon": 122.0813594, "alt": 43.2, "hr": 93, "dist": 0.9, "speed": 0.0, "time": 1, "temp": 28, "cadence": 60}, {"lat": 37.531563, "lon": 122.0813115, "alt": 43.6, "hr": 94, "dist": 4.9, "speed": 0.0, "time": 5, "temp": 28, "cadence": 57}, {"lat": 37.5315825, "lon": 122.0812877, "alt": 44.2, "hr": 94, "dist": 7.7, "speed": 1.7, "time": 7, "temp": 27, "cadence": 57}, {"lat": 37.5315916, "lon": 122.0812789, "alt": 44.4, "hr": 93, "dist": 9.4, "speed": 1.67, "time": 8, "temp": 27, "cadence": 61}, {"lat": 37.5316289, "lon": 122.0812357, "alt": 44.6, "hr": 94, "dist": 15.3, "speed": 1.33, "time": 13, "temp": 27, "cadence": 60}, {"lat": 37.5316807, "lon": 122.0811836, "alt": 44.4, "hr": 97, "dist": 24.8, "speed": 1.47, "time": 19, "temp": 27, "cadence": 64}, {"lat": 37.5316886, "lon": 122.0811576, "alt": 44.2, "hr": 98, "dist": 27.8, "speed": 1.43, "time": 21, "temp": 27, "cadence": 64}, {"lat": 37.5316887, "lon": 122.0811444, "alt": 44.2, "hr": 98, "dist": 29.2, "speed": 1.57, "time": 22, "temp": 27, "cadence": 63}, {"lat": 37.5316885, "lon": 122.0811191, "alt": 44.2, "hr": 99, "dist": 30.0, "speed": 1.57, "time": 24, "temp": 27, "cadence": 63}, {"lat": 37.5316884, "lon": 122.0810968, "alt": 44.0, "hr": 103, "dist": 32.0, "speed": 0.59, "time": 27, "temp": 27, "cadence": 63}, {"lat": 37.5316867, "lon": 122.0810938, "alt": 43.8, "hr": 103, "dist": 32.0, "speed": 0.59, "time": 28, "temp": 27, "cadence": 63}, {"lat": 37.5316746, "lon": 122.0810773, "alt": 43.4, "hr": 102, "dist": 32.1, "speed": 0.62, "time": 31, "temp": 27, "cadence": 62}, {"lat": 37.5316395, "lon": 122.080953, "alt": 43.0, "hr": 99, "dist": 38.3, "speed": 0.84, "time": 40, "temp": 27, "cadence": 62}, {"lat": 37.5316422, "lon": 122.0809382, "alt": 43.0, "hr": 99, "dist": 38.4, "speed": 0.91, "time": 41, "temp": 27, "cadence": 62}, {"lat": 37.5316449, "lon": 122.0809249, "alt": 43.2, "hr": 99, "dist": 39.5, "speed": 0.91, "time": 42, "temp": 27, "cadence": 62}, {"lat": 37.5316574, "lon": 122.0808756, "alt": 42.2, "hr": 98, "dist": 44.3, "speed": 0.94, "time": 47, "temp": 27, "cadence": 98}, {"lat": 37.5316569, "lon": 122.0808525, "alt": 41.0, "hr": 97, "dist": 46.1, "speed": 0.93, "time": 49, "temp": 27, "cadence": 98}, {"lat": 37.5316519, "lon": 122.080826, "alt": 39.8, "hr": 97, "dist": 48.5, "speed": 1.01, "time": 51, "temp": 27, "cadence": 96}, {"lat": 37.5316399, "lon": 122.0807809, "alt": 39.0, "hr": 97, "dist": 53.8, "speed": 1.49, "time": 54, "temp": 27, "cadence": 64}, {"lat": 37.5316306, "lon": 122.0807516, "alt": 39.2, "hr": 97, "dist": 55.7, "speed": 1.59, "time": 56, "temp": 27, "cadence": 62}, {"lat": 37.5315921, "lon": 122.0806461, "alt": 40.6, "hr": 99, "dist": 65.7, "speed": 1.51, "time": 63, "temp": 27, "cadence": 59}, {"lat": 37.5315649, "lon": 122.080485, "alt": 40.0, "hr": 99, "dist": 79.7, "speed": 1.3, "time": 73, "temp": 28, "cadence": 62}, {"lat": 37.5316063, "lon": 122.080386, "alt": 39.2, "hr": 102, "dist": 90.6, "speed": 1.39, "time": 80, "temp": 28, "cadence": 62}, {"lat": 37.5316144, "lon": 122.0803729, "alt": 39.2, "hr": 102, "dist": 92.1, "speed": 1.43, "time": 81, "temp": 28, "cadence": 62}, {"lat": 37.5316853, "lon": 122.0802439, "alt": 39.4, "hr": 104, "dist": 105.4, "speed": 1.4, "time": 91, "temp": 28, "cadence": 62}, {"lat": 37.5317512, "lon": 122.0801442, "alt": 39.4, "hr": 101, "dist": 117.1, "speed": 1.38, "time": 99, "temp": 28, "cadence": 62}, {"lat": 37.5317704, "lon": 122.0801247, "alt": 39.6, "hr": 101, "dist": 119.0, "speed": 1.39, "time": 101, "temp": 28, "cadence": 62}, {"lat": 37.5318327, "lon": 122.0800148, "alt": 39.0, "hr": 101, "dist": 131.6, "speed": 1.41, "time": 109, "temp": 28, "cadence": 63}, {"lat": 37.5318493, "lon": 122.0799903, "alt": 38.8, "hr": 100, "dist": 134.3, "speed": 1.41, "time": 111, "temp": 28, "cadence": 62}, {"lat": 37.5318742, "lon": 122.0799056, "alt": 38.2, "hr": 100, "dist": 142.8, "speed": 1.42, "time": 117, "temp": 28, "cadence": 62}, {"lat": 37.5318685, "lon": 122.0798278, "alt": 37.4, "hr": 101, "dist": 151.4, "speed": 1.41, "time": 123, "temp": 28, "cadence": 57}, {"lat": 37.5318623, "lon": 122.0798192, "alt": 37.4, "hr": 100, "dist": 152.8, "speed": 1.42, "time": 124, "temp": 28, "cadence": 57}, {"lat": 37.5317823, "lon": 122.0797455, "alt": 37.4, "hr": 101, "dist": 163.4, "speed": 1.41, "time": 132, "temp": 28, "cadence": 62}, {"lat": 37.5317134, "lon": 122.0796966, "alt": 37.6, "hr": 99, "dist": 171.5, "speed": 1.44, "time": 137, "temp": 28, "cadence": 62}, {"lat": 37.5317007, "lon": 122.0796857, "alt": 37.4, "hr": 99, "dist": 173.2, "speed": 1.45, "time": 138, "temp": 28, "cadence": 62}, {"lat": 37.5316426, "lon": 122.0796424, "alt": 37.2, "hr": 98, "dist": 180.9, "speed": 1.49, "time": 143, "temp": 28, "cadence": 62}, {"lat": 37.531552, "lon": 122.0795981, "alt": 36.8, "hr": 99, "dist": 192.6, "speed": 1.51, "time": 150, "temp": 28, "cadence": 63}, {"lat": 37.5315074, "lon": 122.0795707, "alt": 36.4, "hr": 100, "dist": 198.1, "speed": 1.54, "time": 153, "temp": 28, "cadence": 63}, {"lat": 37.531426, "lon": 122.07951, "alt": 36.0, "hr": 102, "dist": 208.7, "speed": 1.6, "time": 159, "temp": 28, "cadence": 63}, {"lat": 37.5313506, "lon": 122.0794623, "alt": 35.6, "hr": 103, "dist": 218.0, "speed": 1.58, "time": 166, "temp": 28, "cadence": 62}, {"lat": 37.5313106, "lon": 122.0794405, "alt": 35.4, "hr": 103, "dist": 223.0, "speed": 1.57, "time": 169, "temp": 28, "cadence": 63}, {"lat": 37.5312652, "lon": 122.0794131, "alt": 35.2, "hr": 103, "dist": 228.7, "speed": 1.59, "time": 172, "temp": 28, "cadence": 64}, {"lat": 37.5311526, "lon": 122.0793511, "alt": 34.8, "hr": 103, "dist": 242.6, "speed": 1.64, "time": 180, "temp": 28, "cadence": 64}, {"lat": 37.5310887, "lon": 122.0793239, "alt": 34.2, "hr": 102, "dist": 249.3, "speed": 1.63, "time": 185, "temp": 28, "cadence": 62}, {"lat": 37.5310599, "lon": 122.079312, "alt": 34.0, "hr": 103, "dist": 252.4, "speed": 1.62, "time": 187, "temp": 28, "cadence": 62}, {"lat": 37.5309748, "lon": 122.0792793, "alt": 33.2, "hr": 102, "dist": 262.9, "speed": 1.63, "time": 193, "temp": 28, "cadence": 64}, {"lat": 37.5309143, "lon": 122.079249, "alt": 32.8, "hr": 103, "dist": 270.1, "speed": 1.64, "time": 197, "temp": 28, "cadence": 63}, {"lat": 37.5308736, "lon": 122.0792293, "alt": 32.2, "hr": 103, "dist": 275.2, "speed": 1.67, "time": 200, "temp": 28, "cadence": 61}, {"lat": 37.5308495, "lon": 122.0792125, "alt": 31.8, "hr": 103, "dist": 278.5, "speed": 1.67, "time": 202, "temp": 28, "cadence": 0}, {"lat": 37.5307833, "lon": 122.0791563, "alt": 31.4, "hr": 104, "dist": 287.1, "speed": 1.64, "time": 208, "temp": 28, "cadence": 63}, {"lat": 37.5307709, "lon": 122.0791485, "alt": 31.2, "hr": 104, "dist": 288.8, "speed": 1.64, "time": 209, "temp": 28, "cadence": 62}, {"lat": 37.5306908, "lon": 122.0791063, "alt": 30.4, "hr": 105, "dist": 298.9, "speed": 1.64, "time": 215, "temp": 28, "cadence": 64}, {"lat": 37.5306611, "lon": 122.0790944, "alt": 30.0, "hr": 106, "dist": 302.3, "speed": 1.65, "time": 217, "temp": 28, "cadence": 64}, {"lat": 37.5305748, "lon": 122.0790822, "alt": 29.4, "hr": 107, "dist": 311.7, "speed": 1.66, "time": 223, "temp": 28, "cadence": 63}, {"lat": 37.5305217, "lon": 122.0790765, "alt": 28.8, "hr": 107, "dist": 318.5, "speed": 1.66, "time": 227, "temp": 28, "cadence": 63}, {"lat": 37.5304475, "lon": 122.0790512, "alt": 28.2, "hr": 105, "dist": 326.5, "speed": 1.64, "time": 232, "temp": 28, "cadence": 62}, {"lat": 37.5304189, "lon": 122.0790291, "alt": 27.6, "hr": 105, "dist": 330.1, "speed": 1.65, "time": 234, "temp": 28, "cadence": 63}, {"lat": 37.5303609, "lon": 122.0789373, "alt": 27.4, "hr": 105, "dist": 340.6, "speed": 1.68, "time": 240, "temp": 28, "cadence": 61}, {"lat": 37.5303447, "lon": 122.0788854, "alt": 27.4, "hr": 102, "dist": 345.8, "speed": 1.69, "time": 243, "temp": 28, "cadence": 63}, {"lat": 37.5303172, "lon": 122.0787928, "alt": 27.0, "hr": 100, "dist": 354.9, "speed": 1.71, "time": 248, "temp": 28, "cadence": 61}, {"lat": 37.5302849, "lon": 122.0787225, "alt": 27.0, "hr": 102, "dist": 362.9, "speed": 1.7, "time": 254, "temp": 28, "cadence": 61}, {"lat": 37.5302342, "lon": 122.0786904, "alt": 26.6, "hr": 103, "dist": 369.1, "speed": 1.65, "time": 259, "temp": 28, "cadence": 60}, {"lat": 37.5302114, "lon": 122.0786737, "alt": 26.4, "hr": 104, "dist": 372.2, "speed": 1.63, "time": 261, "temp": 28, "cadence": 61}, {"lat": 37.5300994, "lon": 122.0786016, "alt": 25.6, "hr": 104, "dist": 386.2, "speed": 1.6, "time": 270, "temp": 28, "cadence": 61}, {"lat": 37.5300747, "lon": 122.078587, "alt": 25.6, "hr": 102, "dist": 389.1, "speed": 1.6, "time": 272, "temp": 28, "cadence": 61}, {"lat": 37.5300167, "lon": 122.0785532, "alt": 24.8, "hr": 99, "dist": 396.0, "speed": 1.58, "time": 277, "temp": 28, "cadence": 60}, {"lat": 37.5299484, "lon": 122.0785127, "alt": 24.8, "hr": 99, "dist": 404.2, "speed": 1.55, "time": 282, "temp": 28, "cadence": 62}, {"lat": 37.5299333, "lon": 122.0785023, "alt": 24.4, "hr": 100, "dist": 406.1, "speed": 1.55, "time": 283, "temp": 28, "cadence": 62}, {"lat": 37.5298516, "lon": 122.0784487, "alt": 23.4, "hr": 99, "dist": 416.5, "speed": 1.59, "time": 289, "temp": 28, "cadence": 62}, {"lat": 37.5298379, "lon": 122.0784384, "alt": 23.2, "hr": 100, "dist": 418.4, "speed": 1.59, "time": 290, "temp": 28, "cadence": 63}, {"lat": 37.5297911, "lon": 122.078405, "alt": 23.0, "hr": 99, "dist": 424.8, "speed": 1.61, "time": 294, "temp": 28, "cadence": 64}, {"lat": 37.5297511, "lon": 122.0783816, "alt": 22.8, "hr": 99, "dist": 429.4, "speed": 1.6, "time": 297, "temp": 28, "cadence": 62}, {"lat": 37.5297228, "lon": 122.078364, "alt": 22.2, "hr": 100, "dist": 433.0, "speed": 1.6, "time": 299, "temp": 28, "cadence": 64}, {"lat": 37.5296775, "lon": 122.0783352, "alt": 21.2, "hr": 101, "dist": 438.5, "speed": 1.65, "time": 302, "temp": 28, "cadence": 64}, {"lat": 37.5296633, "lon": 122.0783268, "alt": 20.8, "hr": 101, "dist": 440.4, "speed": 1.67, "time": 303, "temp": 28, "cadence": 64}, {"lat": 37.5296367, "lon": 122.0783098, "alt": 20.2, "hr": 102, "dist": 444.1, "speed": 1.7, "time": 305, "temp": 28, "cadence": 0}, {"lat": 37.529568, "lon": 122.0782614, "alt": 20.6, "hr": 103, "dist": 452.4, "speed": 1.65, "time": 311, "temp": 28, "cadence": 63}, {"lat": 37.5295245, "lon": 122.0782402, "alt": 20.6, "hr": 106, "dist": 457.3, "speed": 1.62, "time": 314, "temp": 28, "cadence": 62}, {"lat": 37.52951, "lon": 122.0782343, "alt": 20.6, "hr": 110, "dist": 459.4, "speed": 1.63, "time": 315, "temp": 28, "cadence": 64}, {"lat": 37.52946, "lon": 122.0782074, "alt": 20.6, "hr": 112, "dist": 465.9, "speed": 1.65, "time": 319, "temp": 28, "cadence": 63}, {"lat": 37.5294034, "lon": 122.0781731, "alt": 20.2, "hr": 112, "dist": 473.3, "speed": 1.61, "time": 326, "temp": 28, "cadence": 0}, {"lat": 37.5293441, "lon": 122.0781353, "alt": 20.4, "hr": 111, "dist": 480.9, "speed": 1.57, "time": 332, "temp": 28, "cadence": 61}, {"alt": 20.4, "hr": 108, "dist": 491.9, "speed": 1.57, "time": 341, "temp": 28, "cadence": 61}, {"alt": 20.4, "hr": 109, "dist": 512.5, "speed": 1.59, "time": 354, "temp": 28, "cadence": 61}, {"lat": 37.5290693, "lon": 122.0777315, "alt": 20.4, "hr": 108, "dist": 533.0, "speed": 1.57, "time": 367, "temp": 28, "cadence": 60}, {"lat": 37.5290739, "lon": 122.0779883, "alt": 20.0, "hr": 105, "dist": 543.9, "speed": 1.54, "time": 374, "temp": 28, "cadence": 58}, {"lat": 37.5291329, "lon": 122.0779332, "alt": 19.0, "hr": 104, "dist": 548.5, "speed": 1.53, "time": 377, "temp": 28, "cadence": 0}, {"lat": 37.5291508, "lon": 122.0778307, "alt": 17.8, "hr": 103, "dist": 553.1, "speed": 1.53, "time": 380, "temp": 28, "cadence": 105}, {"lat": 37.5291004, "lon": 122.0778081, "alt": 16.6, "hr": 103, "dist": 558.4, "speed": 2.01, "time": 383, "temp": 28, "cadence": 0}, {"lat": 37.5291894, "lon": 122.0779114, "alt": 16.2, "hr": 103, "dist": 558.4, "speed": 2.01, "time": 384, "temp": 28, "cadence": 0}, {"alt": 15.0, "hr": 104, "dist": 566.5, "speed": 2.01, "time": 388, "temp": 28, "cadence": 0}, {"alt": 13.8, "hr": 104, "dist": 574.5, "speed": 2.01, "time": 392, "temp": 28, "cadence": 0}, {"alt": 12.8, "hr": 104, "dist": 586.5, "speed": 2.01, "time": 398, "temp": 29, "cadence": 0}, {"lat": 37.5288516, "lon": 122.0777515, "alt": 12.8, "hr": 107, "dist": 604.3, "speed": 1.68, "time": 408, "temp": 28, "cadence": 62}, {"lat": 37.5288445, "lon": 122.0777276, "alt": 12.4, "hr": 109, "dist": 612.7, "speed": 1.66, "time": 414, "temp": 28, "cadence": 62}, {"lat": 37.5288557, "lon": 122.0776984, "alt": 12.6, "hr": 110, "dist": 612.7, "speed": 1.65, "time": 416, "temp": 28, "cadence": 62}, {"lat": 37.5288734, "lon": 122.0776616, "alt": 12.8, "hr": 109, "dist": 613.1, "speed": 1.85, "time": 419, "temp": 28, "cadence": 62}, {"lat": 37.528882, "lon": 122.0776401, "alt": 12.8, "hr": 110, "dist": 615.9, "speed": 1.75, "time": 421, "temp": 28, "cadence": 63}, {"lat": 37.5288898, "lon": 122.0775742, "alt": 12.6, "hr": 110, "dist": 621.3, "speed": 1.55, "time": 425, "temp": 28, "cadence": 59}, {"lat": 37.5288817, "lon": 122.0774611, "alt": 11.6, "hr": 109, "dist": 631.8, "speed": 1.59, "time": 432, "temp": 28, "cadence": 59}, {"lat": 37.528861, "lon": 122.0773233, "alt": 10.4, "hr": 110, "dist": 645.7, "speed": 1.31, "time": 442, "temp": 28, "cadence": 59}, {"lat": 37.5288315, "lon": 122.0772171, "alt": 10.6, "hr": 110, "dist": 657.6, "speed": 1.37, "time": 451, "temp": 29, "cadence": 59}, {"lat": 37.5287817, "lon": 122.0771263, "alt": 10.6, "hr": 107, "dist": 669.3, "speed": 1.52, "time": 459, "temp": 28, "cadence": 59}, {"lat": 37.5287729, "lon": 122.077105, "alt": 10.6, "hr": 107, "dist": 672.0, "speed": 1.39, "time": 461, "temp": 28, "cadence": 59}, {"lat": 37.5287649, "lon": 122.0770405, "alt": 10.4, "hr": 106, "dist": 675.0, "speed": 1.33, "time": 465, "temp": 28, "cadence": 58}, {"lat": 37.5287776, "lon": 122.0769979, "alt": 10.2, "hr": 106, "dist": 678.6, "speed": 1.23, "time": 468, "temp": 28, "cadence": 57}, {"lat": 37.5288436, "lon": 122.0768405, "alt": 10.0, "hr": 104, "dist": 694.8, "speed": 1.22, "time": 481, "temp": 28, "cadence": 58}, {"lat": 37.5288957, "lon": 122.0767151, "alt": 10.0, "hr": 101, "dist": 707.3, "speed": 1.21, "time": 491, "temp": 29, "cadence": 58}, {"lat": 37.5289001, "lon": 122.0767034, "alt": 10.0, "hr": 101, "dist": 708.6, "speed": 1.21, "time": 492, "temp": 28, "cadence": 58}, {"lat": 37.5289597, "lon": 122.0765699, "alt": 9.6, "hr": 101, "dist": 722.5, "speed": 1.18, "time": 503, "temp": 28, "cadence": 58}, {"lat": 37.5289811, "lon": 122.0765118, "alt": 9.4, "hr": 101, "dist": 728.5, "speed": 1.2, "time": 508, "temp": 28, "cadence": 58}, {"lat": 37.5289972, "lon": 122.0764736, "alt": 9.4, "hr": 104, "dist": 731.8, "speed": 1.21, "time": 511, "temp": 28, "cadence": 57}, {"lat": 37.5290086, "lon": 122.0764482, "alt": 9.4, "hr": 105, "dist": 734.9, "speed": 1.2, "time": 513, "temp": 28, "cadence": 57}, {"lat": 37.5290341, "lon": 122.0763905, "alt": 9.4, "hr": 102, "dist": 740.8, "speed": 1.21, "time": 518, "temp": 28, "cadence": 58}, {"lat": 37.5290531, "lon": 122.0763444, "alt": 9.2, "hr": 100, "dist": 745.5, "speed": 1.19, "time": 523, "temp": 28, "cadence": 0}, {"lat": 37.5290933, "lon": 122.076232, "alt": 9.0, "hr": 100, "dist": 756.6, "speed": 1.7, "time": 531, "temp": 28, "cadence": 57}, {"lat": 37.5291425, "lon": 122.0761047, "alt": 9.0, "hr": 100, "dist": 769.9, "speed": 1.47, "time": 541, "temp": 28, "cadence": 56}, {"lat": 37.5291533, "lon": 122.0760734, "alt": 9.0, "hr": 103, "dist": 772.3, "speed": 1.05, "time": 544, "temp": 28, "cadence": 57}, {"lat": 37.52918, "lon": 122.0760049, "alt": 9.2, "hr": 104, "dist": 778.7, "speed": 1.06, "time": 550, "temp": 28, "cadence": 57}, {"lat": 37.5292245, "lon": 122.0758824, "alt": 9.0, "hr": 104, "dist": 791.1, "speed": 0.99, "time": 561, "temp": 28, "cadence": 56}, {"lat": 37.5292722, "lon": 122.075767, "alt": 8.6, "hr": 102, "dist": 802.8, "speed": 1.16, "time": 571, "temp": 29, "cadence": 56}, {"lat": 37.5293155, "lon": 122.0756185, "alt": 8.6, "hr": 101, "dist": 817.1, "speed": 1.17, "time": 583, "temp": 28, "cadence": 56}, {"lat": 37.5293137, "lon": 122.0755448, "alt": 8.6, "hr": 100, "dist": 823.3, "speed": 1.14, "time": 590, "temp": 28, "cadence": 0}, {"lat": 37.5292912, "lon": 122.0754482, "alt": 8.4, "hr": 99, "dist": 832.3, "speed": 1.06, "time": 598, "temp": 28, "cadence": 48}, {"lat": 37.5292883, "lon": 122.0754365, "alt": 8.4, "hr": 99, "dist": 833.4, "speed": 1.07, "time": 599, "temp": 28, "cadence": 48}, {"lat": 37.5292525, "lon": 122.075357, "alt": 8.0, "hr": 99, "dist": 843.5, "speed": 1.14, "time": 608, "temp": 29, "cadence": 54}, {"lat": 37.5292442, "lon": 122.0753512, "alt": 8.0, "hr": 99, "dist": 844.0, "speed": 1.14, "time": 609, "temp": 28, "cadence": 51}, {"lat": 37.5292088, "lon": 122.0752711, "alt": 7.8, "hr": 101, "dist": 852.1, "speed": 1.12, "time": 615, "temp": 29, "cadence": 57}, {"lat": 37.5292364, "lon": 122.0751768, "alt": 7.6, "hr": 102, "dist": 860.1, "speed": 1.06, "time": 622, "temp": 28, "cadence": 56}, {"lat": 37.5292966, "lon": 122.0750962, "alt": 7.4, "hr": 101, "dist": 871.1, "speed": 1.11, "time": 631, "temp": 28, "cadence": 57}, {"lat": 37.5293826, "lon": 122.0750288, "alt": 8.4, "hr": 102, "dist": 883.2, "speed": 1.17, "time": 641, "temp": 28, "cadence": 55}, {"lat": 37.5294564, "lon": 122.0749545, "alt": 8.8, "hr": 97, "dist": 893.3, "speed": 1.08, "time": 650, "temp": 28, "cadence": 55}, {"lat": 37.5294696, "lon": 122.0749366, "alt": 8.8, "hr": 94, "dist": 895.9, "speed": 1.11, "time": 652, "temp": 28, "cadence": 55}, {"lat": 37.5294815, "lon": 122.0749195, "alt": 8.6, "hr": 95, "dist": 898.6, "speed": 1.19, "time": 654, "temp": 28, "cadence": 55}, {"lat": 37.5295058, "lon": 122.0748791, "alt": 8.6, "hr": 96, "dist": 903.0, "speed": 1.14, "time": 658, "temp": 28, "cadence": 56}, {"lat": 37.5295556, "lon": 122.0747777, "alt": 8.4, "hr": 98, "dist": 913.0, "speed": 1.12, "time": 667, "temp": 28, "cadence": 55}, {"lat": 37.5295908, "lon": 122.0746192, "alt": 8.4, "hr": 99, "dist": 928.7, "speed": 1.17, "time": 680, "temp": 28, "cadence": 56}, {"lat": 37.5295894, "lon": 122.0744719, "alt": 8.8, "hr": 100, "dist": 942.1, "speed": 0.95, "time": 692, "temp": 28, "cadence": 56}, {"lat": 37.5295665, "lon": 122.0743906, "alt": 9.0, "hr": 97, "dist": 950.1, "speed": 1.12, "time": 700, "temp": 28, "cadence": 55}, {"lat": 37.5295087, "lon": 122.074297, "alt": 8.4, "hr": 97, "dist": 961.1, "speed": 1.23, "time": 709, "temp": 28, "cadence": 56}, {"lat": 37.5294887, "lon": 122.074268, "alt": 8.4, "hr": 100, "dist": 965.0, "speed": 1.19, "time": 712, "temp": 28, "cadence": 57}, {"lat": 37.5294527, "lon": 122.0742175, "alt": 8.4, "hr": 99, "dist": 971.0, "speed": 1.19, "time": 717, "temp": 28, "cadence": 57}, {"lat": 37.5293781, "lon": 122.0741375, "alt": 8.4, "hr": 100, "dist": 982.0, "speed": 1.22, "time": 726, "temp": 28, "cadence": 56}, {"lat": 37.52931, "lon": 122.0741016, "alt": 8.4, "hr": 101, "dist": 989.8, "speed": 1.19, "time": 733, "temp": 28, "cadence": 0}, {"lat": 37.5292635, "lon": 122.0740672, "alt": 8.4, "hr": 100, "dist": 996.3, "speed": 1.28, "time": 738, "temp": 28, "cadence": 55}, {"lat": 37.5292415, "lon": 122.0740592, "alt": 8.2, "hr": 99, "dist": 998.8, "speed": 1.28, "time": 740, "temp": 28, "cadence": 55}, {"lat": 37.5292104, "lon": 122.0740483, "alt": 8.2, "hr": 99, "dist": 1001.9, "speed": 1.25, "time": 743, "temp": 28, "cadence": 0}, {"lat": 37.5291449, "lon": 122.0740166, "alt": 8.2, "hr": 99, "dist": 1010.3, "speed": 1.21, "time": 749, "temp": 28, "cadence": 55}, {"lat": 37.5290856, "lon": 122.0739703, "alt": 8.2, "hr": 101, "dist": 1017.8, "speed": 1.21, "time": 756, "temp": 28, "cadence": 55}, {"lat": 37.5290223, "lon": 122.073919, "alt": 8.0, "hr": 101, "dist": 1025.4, "speed": 1.12, "time": 764, "temp": 28, "cadence": 55}, {"lat": 37.5289574, "lon": 122.0738952, "alt": 8.0, "hr": 101, "dist": 1032.5, "speed": 1.14, "time": 770, "temp": 28, "cadence": 0}, {"lat": 37.5288998, "lon": 122.0738604, "alt": 8.2, "hr": 101, "dist": 1040.8, "speed": 1.3, "time": 776, "temp": 28, "cadence": 55}, {"lat": 37.5288464, "lon": 122.0738201, "alt": 7.6, "hr": 98, "dist": 1048.3, "speed": 1.02, "time": 783, "temp": 28, "cadence": 53}, {"lat": 37.5288396, "lon": 122.0738177, "alt": 7.6, "hr": 98, "dist": 1049.2, "speed": 0.98, "time": 784, "temp": 28, "cadence": 53}, {"lat": 37.5287982, "lon": 122.0737825, "alt": 7.6, "hr": 98, "dist": 1054.6, "speed": 0.87, "time": 791, "temp": 28, "cadence": 46}, {"lat": 37.5288056, "lon": 122.0737727, "alt": 7.6, "hr": 95, "dist": 1057.1, "speed": 0.73, "time": 796, "temp": 28, "cadence": 47}, {"lat": 37.5288003, "lon": 122.0737773, "alt": 7.6, "hr": 94, "dist": 1057.9, "speed": 0.51, "time": 798, "temp": 28, "cadence": 0}, {"lat": 37.528803, "lon": 122.0737552, "alt": 7.6, "hr": 93, "dist": 1061.1, "speed": 0.0, "time": 803, "temp": 28, "cadence": 0}, {"lat": 37.5288141, "lon": 122.0737615, "alt": 7.8, "hr": 93, "dist": 1062.8, "speed": 0.0, "time": 808, "temp": 28, "cadence": 0}, {"lat": 37.5288003, "lon": 122.0737624, "alt": 7.4, "hr": 92, "dist": 1064.5, "speed": 0.0, "time": 816, "temp": 28, "cadence": 0}, {"lat": 37.5288042, "lon": 122.0737828, "alt": 7.4, "hr": 89, "dist": 1065.1, "speed": 0.0, "time": 825, "temp": 28, "cadence": 0}, {"lat": 37.5288068, "lon": 122.0737918, "alt": 7.4, "hr": 90, "dist": 1065.1, "speed": 0.0, "time": 826, "temp": 28, "cadence": 0}, {"lat": 37.5288269, "lon": 122.0737807, "alt": 7.4, "hr": 90, "dist": 1066.4, "speed": 0.0, "time": 833, "temp": 28, "cadence": 0}, {"lat": 37.5288418, "lon": 122.0737618, "alt": 7.4, "hr": 91, "dist": 1067.5, "speed": 0.0, "time": 842, "temp": 28, "cadence": 0}, {"lat": 37.5288434, "lon": 122.0737578, "alt": 7.6, "hr": 91, "dist": 1067.5, "speed": 0.0, "time": 850, "temp": 28, "cadence": 0}, {"lat": 37.5288435, "lon": 122.0737579, "alt": 7.6, "hr": 87, "dist": 1067.5, "speed": 0.0, "time": 855, "temp": 28, "cadence": 0}, {"lat": 37.5288429, "lon": 122.0737626, "alt": 7.6, "hr": 84, "dist": 1067.5, "speed": 0.0, "time": 864, "temp": 28, "cadence": 0}, {"lat": 37.5288425, "lon": 122.0737648, "alt": 7.8, "hr": 83, "dist": 1067.5, "speed": 0.0, "time": 867, "temp": 28, "cadence": 0}, {"lat": 37.5288397, "lon": 122.0737792, "alt": 7.8, "hr": 86, "dist": 1067.5, "speed": 0.0, "time": 880, "temp": 28, "cadence": 0}, {"lat": 37.5288396, "lon": 122.0737799, "alt": 7.8, "hr": 88, "dist": 1067.5, "speed": 0.0, "time": 888, "temp": 28, "cadence": 0}, {"lat": 37.5288396, "lon": 122.0737803, "alt": 7.8, "hr": 91, "dist": 1067.5, "speed": 0.0, "time": 893, "temp": 28, "cadence": 0}, {"lat": 37.5288395, "lon": 122.0737806, "alt": 7.8, "hr": 90, "dist": 1067.5, "speed": 0.0, "time": 901, "temp": 28, "cadence": 0}, {"lat": 37.5288392, "lon": 122.0737819, "alt": 7.8, "hr": 93, "dist": 1067.5, "speed": 0.0, "time": 906, "temp": 28, "cadence": 0}, {"lat": 37.5288391, "lon": 122.0737825, "alt": 7.8, "hr": 97, "dist": 1067.5, "speed": 0.0, "time": 908, "temp": 28, "cadence": 0}, {"lat": 37.5288386, "lon": 122.0737846, "alt": 7.8, "hr": 99, "dist": 1067.5, "speed": 0.0, "time": 914, "temp": 28, "cadence": 0}, {"lat": 37.5288386, "lon": 122.0737847, "alt": 7.8, "hr": 102, "dist": 1067.5, "speed": 0.0, "time": 916, "temp": 28, "cadence": 0}, {"lat": 37.5288387, "lon": 122.0737846, "alt": 7.8, "hr": 99, "dist": 1067.5, "speed": 0.0, "time": 923, "temp": 28, "cadence": 0}, {"lat": 37.5288389, "lon": 122.0737841, "alt": 7.8, "hr": 98, "dist": 1067.5, "speed": 0.0, "time": 925, "temp": 28, "cadence": 0}, {"lat": 37.5288405, "lon": 122.0737772, "alt": 8.0, "hr": 98, "dist": 1067.5, "speed": 0.0, "time": 937, "temp": 28, "cadence": 0}, {"lat": 37.5288409, "lon": 122.0737763, "alt": 8.0, "hr": 93, "dist": 1067.5, "speed": 0.0, "time": 946, "temp": 28, "cadence": 0}, {"lat": 37.5288407, "lon": 122.0737786, "alt": 8.0, "hr": 91, "dist": 1067.5, "speed": 0.0, "time": 947, "temp": 28, "cadence": 0}, {"lat": 37.5288376, "lon": 122.073782, "alt": 8.0, "hr": 88, "dist": 1067.5, "speed": 0.0, "time": 953, "temp": 28, "cadence": 0}, {"lat": 37.5288376, "lon": 122.0737818, "alt": 8.0, "hr": 87, "dist": 1067.5, "speed": 0.0, "time": 957, "temp": 28, "cadence": 0}, {"lat": 37.5288367, "lon": 122.073783, "alt": 8.0, "hr": 88, "dist": 1067.5, "speed": 0.0, "time": 968, "temp": 28, "cadence": 0}, {"lat": 37.5288363, "lon": 122.0737839, "alt": 8.0, "hr": 85, "dist": 1067.5, "speed": 0.0, "time": 973, "temp": 28, "cadence": 0}, {"lat": 37.5288359, "lon": 122.0737841, "alt": 8.0, "hr": 88, "dist": 1067.5, "speed": 0.0, "time": 979, "temp": 28, "cadence": 0}, {"lat": 37.5288358, "lon": 122.0737841, "alt": 8.0, "hr": 88, "dist": 1067.5, "speed": 0.0, "time": 980, "temp": 28, "cadence": 0}, {"lat": 37.5288349, "lon": 122.073784, "alt": 8.0, "hr": 92, "dist": 1067.5, "speed": 0.0, "time": 992, "temp": 28, "cadence": 0}, {"lat": 37.5288349, "lon": 122.0737829, "alt": 8.0, "hr": 95, "dist": 1067.5, "speed": 0.0, "time": 996, "temp": 28, "cadence": 0}, {"lat": 37.5288353, "lon": 122.0737814, "alt": 8.0, "hr": 96, "dist": 1067.5, "speed": 0.0, "time": 1003, "temp": 27, "cadence": 0}, {"lat": 37.5288358, "lon": 122.0737806, "alt": 8.0, "hr": 93, "dist": 1067.5, "speed": 0.0, "time": 1009, "temp": 28, "cadence": 0}, {"lat": 37.5288361, "lon": 122.0737804, "alt": 8.0, "hr": 90, "dist": 1067.5, "speed": 0.0, "time": 1011, "temp": 27, "cadence": 0}, {"lat": 37.5288361, "lon": 122.0737803, "alt": 8.0, "hr": 90, "dist": 1067.5, "speed": 0.0, "time": 1012, "temp": 28, "cadence": 0}, {"lat": 37.5288384, "lon": 122.0737814, "alt": 8.0, "hr": 90, "dist": 1067.5, "speed": 0.0, "time": 1027, "temp": 27, "cadence": 0}, {"lat": 37.52884, "lon": 122.0737851, "alt": 8.0, "hr": 88, "dist": 1067.5, "speed": 0.0, "time": 1042, "temp": 27, "cadence": 0}, {"lat": 37.52884, "lon": 122.0737876, "alt": 8.0, "hr": 85, "dist": 1067.5, "speed": 0.0, "time": 1050, "temp": 27, "cadence": 0}, {"lat": 37.5288399, "lon": 122.0737889, "alt": 8.0, "hr": 82, "dist": 1067.5, "speed": 0.0, "time": 1054, "temp": 27, "cadence": 0}, {"lat": 37.5288398, "lon": 122.0737897, "alt": 8.0, "hr": 82, "dist": 1067.5, "speed": 0.0, "time": 1056, "temp": 27, "cadence": 0}, {"lat": 37.5288395, "lon": 122.073792, "alt": 8.0, "hr": 85, "dist": 1067.5, "speed": 0.0, "time": 1064, "temp": 27, "cadence": 0}, {"lat": 37.5288388, "lon": 122.0737949, "alt": 7.8, "hr": 83, "dist": 1067.5, "speed": 0.0, "time": 1072, "temp": 27, "cadence": 0}, {"lat": 37.5288389, "lon": 122.0737939, "alt": 7.8, "hr": 83, "dist": 1067.5, "speed": 0.0, "time": 1089, "temp": 27, "cadence": 0}, {"lat": 37.5288405, "lon": 122.0737876, "alt": 8.0, "hr": 84, "dist": 1067.5, "speed": 0.0, "time": 1102, "temp": 27, "cadence": 0}, {"lat": 37.5288398, "lon": 122.0737882, "alt": 8.2, "hr": 83, "dist": 1067.5, "speed": 0.0, "time": 1111, "temp": 27, "cadence": 0}, {"lat": 37.5288392, "lon": 122.0737892, "alt": 8.2, "hr": 80, "dist": 1067.5, "speed": 0.0, "time": 1115, "temp": 27, "cadence": 0}, {"lat": 37.5288379, "lon": 122.0737913, "alt": 8.2, "hr": 78, "dist": 1067.5, "speed": 0.0, "time": 1123, "temp": 27, "cadence": 0}, {"lat": 37.5288375, "lon": 122.0737917, "alt": 8.4, "hr": 80, "dist": 1067.5, "speed": 0.0, "time": 1127, "temp": 27, "cadence": 0}, {"lat": 37.5288373, "lon": 122.0737918, "alt": 8.4, "hr": 77, "dist": 1067.5, "speed": 0.0, "time": 1130, "temp": 27, "cadence": 0}, {"lat": 37.528837, "lon": 122.0737918, "alt": 8.4, "hr": 79, "dist": 1067.5, "speed": 0.0, "time": 1140, "temp": 27, "cadence": 0}, {"lat": 37.5288367, "lon": 122.0737941, "alt": 8.2, "hr": 80, "dist": 1067.5, "speed": 0.0, "time": 1153, "temp": 27, "cadence": 0}, {"lat": 37.5288367, "lon": 122.0737946, "alt": 8.2, "hr": 77, "dist": 1067.5, "speed": 0.0, "time": 1155, "temp": 27, "cadence": 0}, {"lat": 37.5288367, "lon": 122.073795, "alt": 8.2, "hr": 74, "dist": 1067.5, "speed": 0.0, "time": 1157, "temp": 27, "cadence": 0}, {"lat": 37.5288368, "lon": 122.0737958, "alt": 8.2, "hr": 77, "dist": 1067.5, "speed": 0.0, "time": 1161, "temp": 27, "cadence": 0}, {"lat": 37.5288368, "lon": 122.073796, "alt": 8.2, "hr": 84, "dist": 1067.5, "speed": 0.0, "time": 1162, "temp": 27, "cadence": 0}, {"lat": 37.5288372, "lon": 122.0737969, "alt": 8.2, "hr": 85, "dist": 1067.5, "speed": 0.0, "time": 1168, "temp": 27, "cadence": 0}, {"lat": 37.5288384, "lon": 122.0737996, "alt": 8.2, "hr": 87, "dist": 1067.5, "speed": 0.0, "time": 1186, "temp": 27, "cadence": 0}, {"lat": 37.5288394, "lon": 122.0737987, "alt": 8.2, "hr": 88, "dist": 1067.5, "speed": 0.0, "time": 1200, "temp": 27, "cadence": 0}, {"lat": 37.5288395, "lon": 122.0737985, "alt": 8.2, "hr": 84, "dist": 1067.5, "speed": 0.0, "time": 1202, "temp": 27, "cadence": 0}, {"lat": 37.5288394, "lon": 122.0737986, "alt": 8.2, "hr": 88, "dist": 1067.5, "speed": 0.0, "time": 1209, "temp": 27, "cadence": 0}, {"lat": 37.5288388, "lon": 122.0737994, "alt": 8.2, "hr": 85, "dist": 1067.5, "speed": 0.0, "time": 1213, "temp": 27, "cadence": 0}, {"lat": 37.5288386, "lon": 122.0737996, "alt": 8.2, "hr": 84, "dist": 1067.5, "speed": 0.0, "time": 1214, "temp": 27, "cadence": 0}, {"lat": 37.5288383, "lon": 122.0738002, "alt": 8.0, "hr": 81, "dist": 1067.5, "speed": 0.0, "time": 1216, "temp": 27, "cadence": 0}, {"lat": 37.528837, "lon": 122.0738018, "alt": 8.0, "hr": 83, "dist": 1067.5, "speed": 0.0, "time": 1224, "temp": 27, "cadence": 0}, {"lat": 37.5288363, "lon": 122.0738022, "alt": 8.0, "hr": 80, "dist": 1067.5, "speed": 0.0, "time": 1228, "temp": 27, "cadence": 0}, {"lat": 37.5288355, "lon": 122.0738023, "alt": 7.8, "hr": 77, "dist": 1067.5, "speed": 0.0, "time": 1238, "temp": 27, "cadence": 0}, {"lat": 37.5288356, "lon": 122.0738012, "alt": 7.8, "hr": 80, "dist": 1067.5, "speed": 0.0, "time": 1242, "temp": 27, "cadence": 0}, {"lat": 37.5288357, "lon": 122.0738006, "alt": 8.0, "hr": 84, "dist": 1067.5, "speed": 0.0, "time": 1244, "temp": 27, "cadence": 0}, {"lat": 37.5288358, "lon": 122.0738001, "alt": 7.8, "hr": 87, "dist": 1067.5, "speed": 0.0, "time": 1246, "temp": 27, "cadence": 0}, {"lat": 37.5288359, "lon": 122.0737985, "alt": 8.0, "hr": 84, "dist": 1067.5, "speed": 0.0, "time": 1254, "temp": 27, "cadence": 0}, {"lat": 37.5288348, "lon": 122.0738008, "alt": 8.0, "hr": 84, "dist": 1067.5, "speed": 0.0, "time": 1268, "temp": 27, "cadence": 0}, {"lat": 37.5288345, "lon": 122.0738022, "alt": 8.2, "hr": 87, "dist": 1067.5, "speed": 0.0, "time": 1278, "temp": 27, "cadence": 0}, {"lat": 37.5288346, "lon": 122.0738015, "alt": 8.2, "hr": 90, "dist": 1067.5, "speed": 0.0, "time": 1282, "temp": 27, "cadence": 0}, {"lat": 37.528833, "lon": 122.0737936, "alt": 8.2, "hr": 89, "dist": 1067.5, "speed": 0.0, "time": 1290, "temp": 27, "cadence": 0}, {"lat": 37.5288326, "lon": 122.0737881, "alt": 8.0, "hr": 86, "dist": 1070.5, "speed": 0.0, "time": 1294, "temp": 27, "cadence": 0}, {"lat": 37.528833, "lon": 122.0737863, "alt": 8.2, "hr": 86, "dist": 1070.5, "speed": 0.0, "time": 1297, "temp": 27, "cadence": 0}, {"lat": 37.5288346, "lon": 122.0737768, "alt": 8.2, "hr": 88, "dist": 1070.5, "speed": 0.0, "time": 1306, "temp": 27, "cadence": 0}, {"lat": 37.5288333, "lon": 122.073769, "alt": 8.0, "hr": 91, "dist": 1070.5, "speed": 0.0, "time": 1320, "temp": 27, "cadence": 0}, {"lat": 37.5288331, "lon": 122.0737688, "alt": 8.2, "hr": 93, "dist": 1070.5, "speed": 0.0, "time": 1321, "temp": 27, "cadence": 0}, {"lat": 37.5288319, "lon": 122.0737656, "alt": 7.8, "hr": 91, "dist": 1070.5, "speed": 0.0, "time": 1333, "temp": 27, "cadence": 0}, {"lat": 37.5288316, "lon": 122.0737622, "alt": 7.6, "hr": 88, "dist": 1070.5, "speed": 0.0, "time": 1346, "temp": 27, "cadence": 0}, {"lat": 37.5288314, "lon": 122.0737603, "alt": 7.4, "hr": 85, "dist": 1070.5, "speed": 0.0, "time": 1353, "temp": 27, "cadence": 0}, {"lat": 37.5288312, "lon": 122.0737599, "alt": 7.4, "hr": 85, "dist": 1070.5, "speed": 0.0, "time": 1357, "temp": 27, "cadence": 0}, {"lat": 37.5288308, "lon": 122.0737586, "alt": 7.0, "hr": 82, "dist": 1070.5, "speed": 0.0, "time": 1374, "temp": 27, "cadence": 0}, {"lat": 37.5288308, "lon": 122.0737587, "alt": 7.2, "hr": 81, "dist": 1070.5, "speed": 0.0, "time": 1375, "temp": 27, "cadence": 0}, {"lat": 37.5288307, "lon": 122.0737655, "alt": 6.8, "hr": 83, "dist": 1070.5, "speed": 0.0, "time": 1391, "temp": 27, "cadence": 0}, {"lat": 37.5288301, "lon": 122.0737701, "alt": 7.2, "hr": 86, "dist": 1070.5, "speed": 0.0, "time": 1396, "temp": 27, "cadence": 0}, {"lat": 37.5288303, "lon": 122.0737745, "alt": 7.4, "hr": 83, "dist": 1070.5, "speed": 0.0, "time": 1404, "temp": 27, "cadence": 0}, {"lat": 37.5288306, "lon": 122.0737746, "alt": 7.4, "hr": 80, "dist": 1070.5, "speed": 0.0, "time": 1405, "temp": 27, "cadence": 0}, {"lat": 37.5288344, "lon": 122.0737724, "alt": 7.4, "hr": 79, "dist": 1070.5, "speed": 0.0, "time": 1409, "temp": 27, "cadence": 0}, {"lat": 37.5288371, "lon": 122.0737711, "alt": 7.4, "hr": 83, "dist": 1070.5, "speed": 0.0, "time": 1420, "temp": 27, "cadence": 0}, {"lat": 37.5288372, "lon": 122.073771, "alt": 7.4, "hr": 82, "dist": 1070.5, "speed": 0.0, "time": 1421, "temp": 27, "cadence": 0}, {"lat": 37.5288387, "lon": 122.0737706, "alt": 7.4, "hr": 84, "dist": 1070.5, "speed": 0.0, "time": 1436, "temp": 27, "cadence": 0}, {"lat": 37.5288416, "lon": 122.0737595, "alt": 7.4, "hr": 87, "dist": 1070.5, "speed": 0.0, "time": 1442, "temp": 27, "cadence": 0}, {"lat": 37.528839, "lon": 122.0737514, "alt": 7.6, "hr": 85, "dist": 1071.8, "speed": 1.29, "time": 1448, "temp": 27, "cadence": 0}, {"lat": 37.5288387, "lon": 122.0737576, "alt": 7.8, "hr": 85, "dist": 1071.9, "speed": 0.0, "time": 1450, "temp": 27, "cadence": 0}, {"lat": 37.5288372, "lon": 122.0737761, "alt": 7.4, "hr": 85, "dist": 1073.7, "speed": 0.0, "time": 1455, "temp": 27, "cadence": 0}, {"lat": 37.5288349, "lon": 122.0737912, "alt": 7.4, "hr": 87, "dist": 1073.9, "speed": 0.0, "time": 1462, "temp": 27, "cadence": 0}, {"lat": 37.5288244, "lon": 122.0737763, "alt": 7.2, "hr": 87, "dist": 1075.4, "speed": 0.0, "time": 1469, "temp": 27, "cadence": 60}, {"lat": 37.5288283, "lon": 122.0737808, "alt": 7.2, "hr": 90, "dist": 1079.3, "speed": 1.29, "time": 1473, "temp": 27, "cadence": 0}, {"lat": 37.5288234, "lon": 122.0737858, "alt": 7.2, "hr": 91, "dist": 1079.5, "speed": 0.0, "time": 1479, "temp": 27, "cadence": 0}, {"lat": 37.5288228, "lon": 122.0737851, "alt": 7.4, "hr": 95, "dist": 1079.5, "speed": 0.0, "time": 1483, "temp": 27, "cadence": 0}, {"lat": 37.5288241, "lon": 122.0737789, "alt": 7.2, "hr": 88, "dist": 1079.5, "speed": 0.0, "time": 1489, "temp": 27, "cadence": 0}, {"lat": 37.5288246, "lon": 122.0737765, "alt": 7.2, "hr": 87, "dist": 1079.5, "speed": 0.0, "time": 1491, "temp": 27, "cadence": 0}, {"lat": 37.5288279, "lon": 122.0737613, "alt": 7.2, "hr": 91, "dist": 1079.5, "speed": 0.0, "time": 1503, "temp": 27, "cadence": 0}, {"lat": 37.528829, "lon": 122.0737562, "alt": 7.2, "hr": 92, "dist": 1079.5, "speed": 0.0, "time": 1507, "temp": 27, "cadence": 0}, {"lat": 37.5288305, "lon": 122.0737478, "alt": 7.0, "hr": 88, "dist": 1079.5, "speed": 0.0, "time": 1515, "temp": 27, "cadence": 0}, {"lat": 37.5288307, "lon": 122.0737468, "alt": 7.0, "hr": 88, "dist": 1079.5, "speed": 0.0, "time": 1516, "temp": 27, "cadence": 0}, {"lat": 37.5288309, "lon": 122.073746, "alt": 7.0, "hr": 85, "dist": 1079.5, "speed": 0.0, "time": 1517, "temp": 27, "cadence": 0}, {"lat": 37.5288313, "lon": 122.0737416, "alt": 7.0, "hr": 82, "dist": 1079.5, "speed": 0.0, "time": 1526, "temp": 27, "cadence": 0}, {"lat": 37.5288293, "lon": 122.0737462, "alt": 6.8, "hr": 79, "dist": 1079.5, "speed": 0.0, "time": 1537, "temp": 27, "cadence": 0}, {"lat": 37.5288283, "lon": 122.0737491, "alt": 6.8, "hr": 79, "dist": 1079.5, "speed": 0.0, "time": 1541, "temp": 27, "cadence": 0}, {"lat": 37.5288278, "lon": 122.0737535, "alt": 6.8, "hr": 78, "dist": 1079.5, "speed": 0.0, "time": 1552, "temp": 27, "cadence": 0}, {"lat": 37.5288292, "lon": 122.0737551, "alt": 6.8, "hr": 81, "dist": 1079.5, "speed": 0.0, "time": 1561, "temp": 27, "cadence": 0}, {"lat": 37.5288288, "lon": 122.0737642, "alt": 7.0, "hr": 79, "dist": 1079.5, "speed": 0.0, "time": 1572, "temp": 27, "cadence": 0}, {"lat": 37.5288297, "lon": 122.0737829, "alt": 7.0, "hr": 81, "dist": 1079.5, "speed": 0.0, "time": 1582, "temp": 27, "cadence": 0}, {"lat": 37.5288288, "lon": 122.0737892, "alt": 6.8, "hr": 81, "dist": 1079.7, "speed": 0.0, "time": 1590, "temp": 27, "cadence": 0}, {"lat": 37.5288293, "lon": 122.0737874, "alt": 7.0, "hr": 85, "dist": 1079.7, "speed": 0.0, "time": 1595, "temp": 27, "cadence": 0}, {"lat": 37.5288295, "lon": 122.0737849, "alt": 6.8, "hr": 86, "dist": 1079.7, "speed": 0.0, "time": 1599, "temp": 27, "cadence": 0}, {"lat": 37.5288293, "lon": 122.0737811, "alt": 6.8, "hr": 83, "dist": 1079.7, "speed": 0.0, "time": 1604, "temp": 27, "cadence": 0}, {"lat": 37.5288292, "lon": 122.0737799, "alt": 6.8, "hr": 80, "dist": 1079.7, "speed": 0.0, "time": 1606, "temp": 27, "cadence": 0}, {"lat": 37.5288288, "lon": 122.0737785, "alt": 6.8, "hr": 82, "dist": 1079.7, "speed": 0.0, "time": 1609, "temp": 27, "cadence": 0}, {"lat": 37.5288288, "lon": 122.0737752, "alt": 6.6, "hr": 87, "dist": 1079.7, "speed": 0.0, "time": 1612, "temp": 27, "cadence": 0}, {"lat": 37.5288284, "lon": 122.0737744, "alt": 6.6, "hr": 89, "dist": 1079.7, "speed": 0.0, "time": 1614, "temp": 27, "cadence": 0}, {"lat": 37.5288278, "lon": 122.073774, "alt": 6.6, "hr": 88, "dist": 1079.7, "speed": 0.0, "time": 1617, "temp": 27, "cadence": 0}, {"lat": 37.5288293, "lon": 122.0737808, "alt": 6.8, "hr": 86, "dist": 1079.7, "speed": 0.0, "time": 1628, "temp": 27, "cadence": 0}, {"lat": 37.5288297, "lon": 122.07378, "alt": 6.6, "hr": 85, "dist": 1079.7, "speed": 0.0, "time": 1635, "temp": 27, "cadence": 0}, {"lat": 37.5288309, "lon": 122.0737763, "alt": 6.6, "hr": 88, "dist": 1079.7, "speed": 0.0, "time": 1644, "temp": 27, "cadence": 0}, {"lat": 37.5288313, "lon": 122.0737753, "alt": 6.6, "hr": 90, "dist": 1079.7, "speed": 0.0, "time": 1646, "temp": 27, "cadence": 0}, {"lat": 37.5288321, "lon": 122.0737722, "alt": 6.6, "hr": 87, "dist": 1079.7, "speed": 0.0, "time": 1651, "temp": 27, "cadence": 0}, {"lat": 37.5288343, "lon": 122.0737673, "alt": 6.6, "hr": 87, "dist": 1079.7, "speed": 0.0, "time": 1658, "temp": 27, "cadence": 0}, {"lat": 37.528826, "lon": 122.0737499, "alt": 6.8, "hr": 86, "dist": 1081.0, "speed": 0.0, "time": 1667, "temp": 27, "cadence": 0}, {"lat": 37.5288324, "lon": 122.0737675, "alt": 6.8, "hr": 86, "dist": 1082.5, "speed": 0.0, "time": 1673, "temp": 27, "cadence": 0}, {"lat": 37.5288361, "lon": 122.0737925, "alt": 6.8, "hr": 86, "dist": 1084.0, "speed": 0.0, "time": 1678, "temp": 27, "cadence": 0}, {"lat": 37.5288367, "lon": 122.0737933, "alt": 7.0, "hr": 87, "dist": 1084.0, "speed": 0.0, "time": 1686, "temp": 27, "cadence": 0}, {"lat": 37.5288406, "lon": 122.0737877, "alt": 6.8, "hr": 87, "dist": 1084.0, "speed": 0.0, "time": 1693, "temp": 27, "cadence": 0}, {"lat": 37.5288425, "lon": 122.0737855, "alt": 7.0, "hr": 84, "dist": 1084.0, "speed": 0.0, "time": 1696, "temp": 27, "cadence": 0}, {"lat": 37.5288483, "lon": 122.0737806, "alt": 6.8, "hr": 80, "dist": 1084.0, "speed": 0.0, "time": 1704, "temp": 27, "cadence": 0}, {"lat": 37.5288498, "lon": 122.0737798, "alt": 6.8, "hr": 77, "dist": 1084.0, "speed": 0.0, "time": 1706, "temp": 27, "cadence": 0}, {"lat": 37.5288506, "lon": 122.0737795, "alt": 6.8, "hr": 77, "dist": 1084.0, "speed": 0.0, "time": 1707, "temp": 27, "cadence": 0}, {"lat": 37.5288553, "lon": 122.0737776, "alt": 6.8, "hr": 74, "dist": 1084.0, "speed": 0.0, "time": 1713, "temp": 27, "cadence": 0}, {"lat": 37.528859, "lon": 122.0737762, "alt": 6.8, "hr": 74, "dist": 1084.0, "speed": 0.0, "time": 1719, "temp": 27, "cadence": 0}, {"lat": 37.5288559, "lon": 122.0737895, "alt": 6.8, "hr": 75, "dist": 1084.8, "speed": 0.0, "time": 1731, "temp": 27, "cadence": 0}, {"lat": 37.5288446, "lon": 122.0738271, "alt": 7.0, "hr": 76, "dist": 1088.8, "speed": 0.0, "time": 1738, "temp": 27, "cadence": 0}, {"lat": 37.5288332, "lon": 122.0738458, "alt": 7.2, "hr": 77, "dist": 1090.3, "speed": 0.0, "time": 1745, "temp": 27, "cadence": 0}, {"lat": 37.5288264, "lon": 122.0738981, "alt": 6.8, "hr": 77, "dist": 1095.8, "speed": 0.73, "time": 1751, "temp": 27, "cadence": 47}, {"lat": 37.5288231, "lon": 122.0739196, "alt": 6.6, "hr": 77, "dist": 1098.2, "speed": 1.07, "time": 1753, "temp": 27, "cadence": 0}, {"lat": 37.5288174, "lon": 122.0739408, "alt": 6.4, "hr": 77, "dist": 1098.9, "speed": 1.16, "time": 1755, "temp": 27, "cadence": 48}, {"lat": 37.5288004, "lon": 122.0739918, "alt": 7.0, "hr": 78, "dist": 1105.6, "speed": 0.96, "time": 1762, "temp": 27, "cadence": 0}, {"lat": 37.5287834, "lon": 122.0739607, "alt": 6.8, "hr": 77, "dist": 1107.8, "speed": 0.0, "time": 1768, "temp": 27, "cadence": 0}, {"lat": 37.5287831, "lon": 122.0739597, "alt": 6.8, "hr": 80, "dist": 1107.9, "speed": 0.71, "time": 1769, "temp": 27, "cadence": 0}, {"lat": 37.5287831, "lon": 122.0739593, "alt": 6.8, "hr": 84, "dist": 1108.4, "speed": 0.71, "time": 1770, "temp": 27, "cadence": 0}, {"lat": 37.5287833, "lon": 122.0739591, "alt": 7.0, "hr": 87, "dist": 1108.4, "speed": 0.0, "time": 1772, "temp": 27, "cadence": 0}, {"lat": 37.5287841, "lon": 122.0739591, "alt": 7.0, "hr": 87, "dist": 1108.4, "speed": 0.0, "time": 1775, "temp": 27, "cadence": 0}, {"lat": 37.5287852, "lon": 122.0739585, "alt": 7.0, "hr": 87, "dist": 1108.7, "speed": 0.0, "time": 1782, "temp": 27, "cadence": 0}, {"lat": 37.5287903, "lon": 122.0739596, "alt": 6.8, "hr": 87, "dist": 1108.7, "speed": 0.0, "time": 1795, "temp": 27, "cadence": 0}, {"lat": 37.528821, "lon": 122.0739721, "alt": 7.0, "hr": 84, "dist": 1110.6, "speed": 0.0, "time": 1809, "temp": 27, "cadence": 0}, {"lat": 37.5288306, "lon": 122.0739736, "alt": 7.2, "hr": 85, "dist": 1111.9, "speed": 0.0, "time": 1810, "temp": 27, "cadence": 0}, {"lat": 37.5288548, "lon": 122.0739737, "alt": 7.2, "hr": 85, "dist": 1113.1, "speed": 1.35, "time": 1812, "temp": 27, "cadence": 0}, {"lat": 37.5288941, "lon": 122.0739748, "alt": 7.2, "hr": 86, "dist": 1118.2, "speed": 1.32, "time": 1815, "temp": 27, "cadence": 0}, {"lat": 37.5289034, "lon": 122.0739741, "alt": 7.2, "hr": 86, "dist": 1119.5, "speed": 1.72, "time": 1816, "temp": 27, "cadence": 0}, {"lat": 37.5289277, "lon": 122.0739772, "alt": 7.2, "hr": 86, "dist": 1121.5, "speed": 1.49, "time": 1818, "temp": 27, "cadence": 0}, {"lat": 37.5289507, "lon": 122.0739804, "alt": 7.2, "hr": 87, "dist": 1124.2, "speed": 1.22, "time": 1820, "temp": 27, "cadence": 0}, {"lat": 37.529014, "lon": 122.0740129, "alt": 6.8, "hr": 86, "dist": 1130.6, "speed": 1.27, "time": 1826, "temp": 27, "cadence": 0}, {"lat": 37.5290641, "lon": 122.0740492, "alt": 6.4, "hr": 87, "dist": 1137.3, "speed": 1.3, "time": 1831, "temp": 27, "cadence": 55}, {"lat": 37.5291081, "lon": 122.074079, "alt": 6.6, "hr": 90, "dist": 1142.0, "speed": 1.3, "time": 1835, "temp": 27, "cadence": 55}, {"lat": 37.5291176, "lon": 122.0740881, "alt": 6.6, "hr": 91, "dist": 1143.6, "speed": 1.3, "time": 1836, "temp": 27, "cadence": 55}, {"lat": 37.529165, "lon": 122.074138, "alt": 6.8, "hr": 90, "dist": 1149.7, "speed": 1.16, "time": 1842, "temp": 27, "cadence": 57}, {"lat": 37.5292038, "lon": 122.0742068, "alt": 6.8, "hr": 89, "dist": 1159.0, "speed": 1.24, "time": 1849, "temp": 27, "cadence": 56}, {"lat": 37.5292491, "lon": 122.0742938, "alt": 6.6, "hr": 91, "dist": 1168.3, "speed": 1.3, "time": 1856, "temp": 27, "cadence": 56}, {"lat": 37.5292764, "lon": 122.0743686, "alt": 6.6, "hr": 90, "dist": 1175.7, "speed": 1.29, "time": 1862, "temp": 27, "cadence": 57}, {"lat": 37.5292858, "lon": 122.0744155, "alt": 6.6, "hr": 87, "dist": 1179.3, "speed": 1.31, "time": 1865, "temp": 27, "cadence": 57}, {"lat": 37.5292967, "lon": 122.0744875, "alt": 6.6, "hr": 88, "dist": 1184.8, "speed": 1.27, "time": 1870, "temp": 27, "cadence": 56}, {"lat": 37.5292942, "lon": 122.0745876, "alt": 6.8, "hr": 88, "dist": 1193.1, "speed": 1.06, "time": 1878, "temp": 27, "cadence": 57}, {"lat": 37.5292815, "lon": 122.0746912, "alt": 6.8, "hr": 90, "dist": 1202.2, "speed": 1.29, "time": 1885, "temp": 27, "cadence": 57}, {"lat": 37.5292681, "lon": 122.0748218, "alt": 6.8, "hr": 91, "dist": 1213.4, "speed": 1.24, "time": 1894, "temp": 27, "cadence": 57}, {"lat": 37.5292489, "lon": 122.0749229, "alt": 6.6, "hr": 92, "dist": 1223.6, "speed": 1.24, "time": 1902, "temp": 27, "cadence": 57}, {"lat": 37.5292319, "lon": 122.0750231, "alt": 6.6, "hr": 93, "dist": 1232.6, "speed": 1.27, "time": 1909, "temp": 27, "cadence": 56}, {"lat": 37.5292152, "lon": 122.0751049, "alt": 6.6, "hr": 94, "dist": 1240.3, "speed": 1.25, "time": 1916, "temp": 27, "cadence": 56}, {"lat": 37.5292011, "lon": 122.0752205, "alt": 6.8, "hr": 97, "dist": 1249.5, "speed": 1.23, "time": 1923, "temp": 27, "cadence": 56}, {"lat": 37.5292, "lon": 122.0752465, "alt": 6.8, "hr": 98, "dist": 1251.8, "speed": 1.26, "time": 1925, "temp": 27, "cadence": 57}, {"lat": 37.5292006, "lon": 122.0752706, "alt": 6.8, "hr": 101, "dist": 1253.9, "speed": 1.26, "time": 1928, "temp": 26, "cadence": 57}, {"lat": 37.5292111, "lon": 122.0752694, "alt": 6.8, "hr": 101, "dist": 1256.2, "speed": 1.25, "time": 1930, "temp": 27, "cadence": 56}, {"lat": 37.529223, "lon": 122.0752664, "alt": 6.8, "hr": 100, "dist": 1256.5, "speed": 1.25, "time": 1931, "temp": 27, "cadence": 56}, {"lat": 37.5293017, "lon": 122.0752248, "alt": 6.8, "hr": 100, "dist": 1263.4, "speed": 1.2, "time": 1937, "temp": 27, "cadence": 56}, {"lat": 37.5293607, "lon": 122.0752015, "alt": 7.0, "hr": 99, "dist": 1271.1, "speed": 1.24, "time": 1943, "temp": 27, "cadence": 55}, {"lat": 37.5293828, "lon": 122.0751938, "alt": 7.0, "hr": 96, "dist": 1274.3, "speed": 1.24, "time": 1946, "temp": 27, "cadence": 57}, {"lat": 37.5294252, "lon": 122.0751501, "alt": 7.0, "hr": 95, "dist": 1280.6, "speed": 1.19, "time": 1951, "temp": 27, "cadence": 56}, {"lat": 37.5294791, "lon": 122.0750865, "alt": 7.0, "hr": 94, "dist": 1289.2, "speed": 1.19, "time": 1958, "temp": 26, "cadence": 56}, {"lat": 37.52951, "lon": 122.0750371, "alt": 7.0, "hr": 93, "dist": 1295.2, "speed": 1.22, "time": 1963, "temp": 27, "cadence": 56}, {"lat": 37.5295635, "lon": 122.0749635, "alt": 7.0, "hr": 91, "dist": 1304.5, "speed": 1.22, "time": 1970, "temp": 26, "cadence": 56}, {"lat": 37.5296126, "lon": 122.0748988, "alt": 7.4, "hr": 92, "dist": 1310.8, "speed": 1.22, "time": 1976, "temp": 26, "cadence": 55}, {"lat": 37.529625, "lon": 122.07489, "alt": 7.6, "hr": 91, "dist": 1311.7, "speed": 1.22, "time": 1977, "temp": 27, "cadence": 55}, {"lat": 37.529686, "lon": 122.07485, "alt": 7.6, "hr": 93, "dist": 1319.9, "speed": 1.25, "time": 1983, "temp": 27, "cadence": 57}, {"lat": 37.5297602, "lon": 122.0747951, "alt": 7.8, "hr": 96, "dist": 1329.8, "speed": 1.22, "time": 1991, "temp": 27, "cadence": 57}, {"lat": 37.5298114, "lon": 122.0747161, "alt": 7.6, "hr": 98, "dist": 1339.6, "speed": 1.26, "time": 1998, "temp": 26, "cadence": 57}, {"lat": 37.5298545, "lon": 122.074619, "alt": 7.8, "hr": 96, "dist": 1349.5, "speed": 1.27, "time": 2006, "temp": 27, "cadence": 57}, {"lat": 37.5299104, "lon": 122.0745409, "alt": 7.8, "hr": 97, "dist": 1358.2, "speed": 1.26, "time": 2013, "temp": 26, "cadence": 57}, {"lat": 37.5299411, "lon": 122.0745278, "alt": 7.6, "hr": 97, "dist": 1362.0, "speed": 1.28, "time": 2016, "temp": 26, "cadence": 57}, {"lat": 37.5299739, "lon": 122.0745367, "alt": 8.0, "hr": 97, "dist": 1364.3, "speed": 1.26, "time": 2019, "temp": 26, "cadence": 57}, {"lat": 37.5300565, "lon": 122.07457, "alt": 8.6, "hr": 97, "dist": 1374.4, "speed": 1.26, "time": 2026, "temp": 26, "cadence": 54}, {"lat": 37.5301199, "lon": 122.0746043, "alt": 8.8, "hr": 99, "dist": 1383.6, "speed": 1.32, "time": 2033, "temp": 26, "cadence": 55}, {"lat": 37.5301875, "lon": 122.0746188, "alt": 9.0, "hr": 102, "dist": 1390.6, "speed": 1.26, "time": 2039, "temp": 26, "cadence": 56}, {"lat": 37.5302643, "lon": 122.0746527, "alt": 9.2, "hr": 104, "dist": 1400.9, "speed": 1.32, "time": 2046, "temp": 26, "cadence": 56}, {"lat": 37.5303472, "lon": 122.0746949, "alt": 9.4, "hr": 106, "dist": 1410.6, "speed": 1.36, "time": 2053, "temp": 26, "cadence": 55}, {"lat": 37.530415, "lon": 122.0747337, "alt": 9.4, "hr": 108, "dist": 1420.4, "speed": 1.35, "time": 2060, "temp": 26, "cadence": 56}, {"lat": 37.5304433, "lon": 122.0747531, "alt": 9.6, "hr": 107, "dist": 1424.2, "speed": 1.36, "time": 2063, "temp": 26, "cadence": 57}, {"lat": 37.5304987, "lon": 122.0747854, "alt": 10.0, "hr": 108, "dist": 1430.1, "speed": 1.32, "time": 2068, "temp": 26, "cadence": 56}, {"lat": 37.5305751, "lon": 122.0748289, "alt": 10.0, "hr": 108, "dist": 1438.7, "speed": 1.32, "time": 2075, "temp": 26, "cadence": 56}, {"lat": 37.5306501, "lon": 122.074875, "alt": 10.6, "hr": 105, "dist": 1447.3, "speed": 1.29, "time": 2082, "temp": 26, "cadence": 56}, {"lat": 37.5306615, "lon": 122.0748844, "alt": 10.8, "hr": 105, "dist": 1448.3, "speed": 1.29, "time": 2083, "temp": 26, "cadence": 56}, {"lat": 37.5307324, "lon": 122.0749305, "alt": 11.0, "hr": 104, "dist": 1457.5, "speed": 1.28, "time": 2090, "temp": 26, "cadence": 56}, {"lat": 37.5308033, "lon": 122.0750029, "alt": 10.8, "hr": 105, "dist": 1467.7, "speed": 1.26, "time": 2098, "temp": 26, "cadence": 55}, {"lat": 37.5308565, "lon": 122.0750863, "alt": 11.2, "hr": 105, "dist": 1477.5, "speed": 1.29, "time": 2105, "temp": 26, "cadence": 54}, {"lat": 37.5309048, "lon": 122.0751516, "alt": 11.6, "hr": 105, "dist": 1485.1, "speed": 1.28, "time": 2111, "temp": 26, "cadence": 56}, {"lat": 37.5309107, "lon": 122.0751658, "alt": 11.8, "hr": 105, "dist": 1487.0, "speed": 1.28, "time": 2112, "temp": 26, "cadence": 56}, {"lat": 37.5309147, "lon": 122.0752098, "alt": 11.8, "hr": 106, "dist": 1491.5, "speed": 1.31, "time": 2115, "temp": 26, "cadence": 56}, {"lat": 37.5309129, "lon": 122.0752582, "alt": 12.0, "hr": 106, "dist": 1494.9, "speed": 1.31, "time": 2118, "temp": 26, "cadence": 57}, {"lat": 37.5309153, "lon": 122.0753235, "alt": 12.4, "hr": 108, "dist": 1497.4, "speed": 1.3, "time": 2123, "temp": 26, "cadence": 57}, {"lat": 37.5309123, "lon": 122.0753345, "alt": 12.2, "hr": 108, "dist": 1498.1, "speed": 1.26, "time": 2124, "temp": 26, "cadence": 57}, {"lat": 37.530904, "lon": 122.0753605, "alt": 11.6, "hr": 108, "dist": 1499.6, "speed": 0.96, "time": 2129, "temp": 26, "cadence": 57}, {"alt": 11.6, "hr": 107, "dist": 1500.4, "speed": 0.0, "time": 2138, "temp": 26, "cadence": 0}, {"alt": 11.4, "hr": 104, "dist": 1501.7, "speed": 0.0, "time": 2147, "temp": 26, "cadence": 0}, {"alt": 11.4, "hr": 103, "dist": 1501.7, "speed": 0.0, "time": 2149, "temp": 26, "cadence": 0}, {"alt": 11.2, "hr": 103, "dist": 1502.5, "speed": 0.0, "time": 2156, "temp": 26, "cadence": 0}, {"alt": 11.6, "hr": 98, "dist": 1504.8, "speed": 0.0, "time": 2165, "temp": 26, "cadence": 0}, {"alt": 11.6, "hr": 95, "dist": 1504.8, "speed": 0.0, "time": 2167, "temp": 26, "cadence": 0}, {"alt": 11.6, "hr": 92, "dist": 1504.8, "speed": 0.0, "time": 2176, "temp": 26, "cadence": 0}, {"alt": 11.6, "hr": 86, "dist": 1504.8, "speed": 0.0, "time": 2190, "temp": 26, "cadence": 0}, {"alt": 11.6, "hr": 83, "dist": 1504.8, "speed": 0.0, "time": 2209, "temp": 26, "cadence": 0}, {"alt": 11.6, "hr": 80, "dist": 1504.8, "speed": 0.0, "time": 2211, "temp": 26, "cadence": 0}, {"alt": 11.6, "hr": 83, "dist": 1504.8, "speed": 0.0, "time": 2215, "temp": 26, "cadence": 0}, {"alt": 11.6, "hr": 87, "dist": 1504.8, "speed": 0.0, "time": 2217, "temp": 26, "cadence": 0}, {"alt": 11.4, "hr": 90, "dist": 1504.8, "speed": 0.0, "time": 2243, "temp": 26, "cadence": 0}, {"alt": 11.4, "hr": 87, "dist": 1509.3, "speed": 0.0, "time": 2288, "temp": 26, "cadence": 0}, {"alt": 11.4, "hr": 90, "dist": 1509.3, "speed": 0.0, "time": 2299, "temp": 26, "cadence": 0}, {"alt": 11.4, "hr": 93, "dist": 1509.3, "speed": 0.0, "time": 2302, "temp": 26, "cadence": 0}, {"alt": 11.6, "hr": 89, "dist": 1509.3, "speed": 0.0, "time": 2318, "temp": 26, "cadence": 0}, {"alt": 11.4, "hr": 86, "dist": 1509.3, "speed": 0.0, "time": 2322, "temp": 26, "cadence": 0}, {"alt": 11.6, "hr": 83, "dist": 1509.3, "speed": 0.0, "time": 2329, "temp": 26, "cadence": 0}, {"alt": 11.4, "hr": 86, "dist": 1509.3, "speed": 0.0, "time": 2337, "temp": 26, "cadence": 0}, {"alt": 11.2, "hr": 89, "dist": 1509.3, "speed": 0.0, "time": 2355, "temp": 26, "cadence": 0}, {"alt": 11.2, "hr": 86, "dist": 1509.3, "speed": 0.0, "time": 2371, "temp": 26, "cadence": 0}, {"alt": 11.4, "hr": 89, "dist": 1509.3, "speed": 0.0, "time": 2383, "temp": 26, "cadence": 0}, {"alt": 11.2, "hr": 86, "dist": 1509.3, "speed": 0.0, "time": 2396, "temp": 26, "cadence": 0}, {"alt": 11.2, "hr": 83, "dist": 1509.3, "speed": 0.0, "time": 2397, "temp": 26, "cadence": 0}, {"alt": 11.2, "hr": 86, "dist": 1513.8, "speed": 0.0, "time": 2422, "temp": 27, "cadence": 0}, {"alt": 11.2, "hr": 89, "dist": 1513.8, "speed": 0.0, "time": 2424, "temp": 26, "cadence": 0}, {"alt": 11.2, "hr": 86, "dist": 1517.6, "speed": 0.0, "time": 2463, "temp": 26, "cadence": 0}, {"lat": 37.5309215, "lon": 122.0752672, "alt": 11.4, "hr": 89, "dist": 1524.9, "speed": 0.95, "time": 2477, "temp": 26, "cadence": 56}, {"lat": 37.5309272, "lon": 122.0752541, "alt": 11.2, "hr": 91, "dist": 1530.3, "speed": 1.2, "time": 2478, "temp": 26, "cadence": 57}, {"lat": 37.5309535, "lon": 122.0752129, "alt": 11.0, "hr": 94, "dist": 1530.3, "speed": 2.66, "time": 2481, "temp": 26, "cadence": 57}, {"lat": 37.5309891, "lon": 122.0751945, "alt": 10.8, "hr": 97, "dist": 1535.0, "speed": 1.93, "time": 2484, "temp": 26, "cadence": 60}, {"lat": 37.5310006, "lon": 122.0751964, "alt": 10.8, "hr": 98, "dist": 1537.1, "speed": 1.93, "time": 2485, "temp": 26, "cadence": 60}, {"lat": 37.5310415, "lon": 122.075208, "alt": 11.0, "hr": 96, "dist": 1542.5, "speed": 1.69, "time": 2489, "temp": 26, "cadence": 57}, {"lat": 37.5311067, "lon": 122.0752264, "alt": 11.2, "hr": 96, "dist": 1550.9, "speed": 1.65, "time": 2495, "temp": 26, "cadence": 58}, {"lat": 37.5312131, "lon": 122.075271, "alt": 11.6, "hr": 97, "dist": 1563.2, "speed": 1.5, "time": 2503, "temp": 26, "cadence": 57}, {"lat": 37.5312871, "lon": 122.0753171, "alt": 11.8, "hr": 100, "dist": 1571.9, "speed": 1.4, "time": 2510, "temp": 26, "cadence": 58}, {"lat": 37.5313628, "lon": 122.0753591, "alt": 11.6, "hr": 103, "dist": 1581.1, "speed": 1.25, "time": 2517, "temp": 26, "cadence": 58}, {"lat": 37.531401, "lon": 122.075379, "alt": 11.8, "hr": 104, "dist": 1585.0, "speed": 1.27, "time": 2520, "temp": 26, "cadence": 59}, {"lat": 37.5315388, "lon": 122.0754754, "alt": 12.4, "hr": 104, "dist": 1601.9, "speed": 1.32, "time": 2532, "temp": 26, "cadence": 59}, {"lat": 37.5316498, "lon": 122.075546, "alt": 12.4, "hr": 106, "dist": 1615.1, "speed": 1.33, "time": 2542, "temp": 26, "cadence": 59}, {"lat": 37.5317601, "lon": 122.0756019, "alt": 11.8, "hr": 109, "dist": 1628.8, "speed": 1.34, "time": 2551, "temp": 26, "cadence": 59}, {"lat": 37.5317944, "lon": 122.0756214, "alt": 12.0, "hr": 109, "dist": 1633.3, "speed": 1.37, "time": 2554, "temp": 26, "cadence": 59}, {"lat": 37.5318827, "lon": 122.0756803, "alt": 12.8, "hr": 109, "dist": 1644.6, "speed": 1.43, "time": 2562, "temp": 26, "cadence": 61}, {"lat": 37.5319323, "lon": 122.0757116, "alt": 12.8, "hr": 109, "dist": 1649.5, "speed": 1.39, "time": 2566, "temp": 26, "cadence": 59}, {"lat": 37.5320677, "lon": 122.0758031, "alt": 12.4, "hr": 109, "dist": 1666.1, "speed": 1.42, "time": 2577, "temp": 26, "cadence": 60}, {"lat": 37.5321781, "lon": 122.0758826, "alt": 12.8, "hr": 109, "dist": 1681.3, "speed": 1.49, "time": 2587, "temp": 26, "cadence": 60}, {"lat": 37.5323317, "lon": 122.0759764, "alt": 13.6, "hr": 109, "dist": 1699.5, "speed": 1.49, "time": 2599, "temp": 26, "cadence": 60}, {"lat": 37.5324185, "lon": 122.0760318, "alt": 13.8, "hr": 109, "dist": 1711.3, "speed": 1.51, "time": 2607, "temp": 26, "cadence": 59}, {"lat": 37.5325651, "lon": 122.0761197, "alt": 14.0, "hr": 109, "dist": 1728.8, "speed": 1.48, "time": 2619, "temp": 26, "cadence": 59}, {"lat": 37.5326771, "lon": 122.0761847, "alt": 13.6, "hr": 106, "dist": 1741.8, "speed": 1.47, "time": 2628, "temp": 26, "cadence": 61}, {"lat": 37.532709, "lon": 122.0762054, "alt": 13.8, "hr": 106, "dist": 1746.7, "speed": 1.48, "time": 2631, "temp": 26, "cadence": 61}, {"lat": 37.5328221, "lon": 122.0762727, "alt": 14.4, "hr": 107, "dist": 1760.3, "speed": 1.47, "time": 2641, "temp": 26, "cadence": 61}, {"lat": 37.5328669, "lon": 122.0763044, "alt": 14.0, "hr": 110, "dist": 1767.0, "speed": 1.47, "time": 2645, "temp": 26, "cadence": 61}, {"lat": 37.5329449, "lon": 122.0763441, "alt": 14.2, "hr": 112, "dist": 1774.7, "speed": 1.47, "time": 2651, "temp": 26, "cadence": 60}, {"lat": 37.5330584, "lon": 122.0764225, "alt": 14.8, "hr": 112, "dist": 1789.3, "speed": 1.45, "time": 2661, "temp": 26, "cadence": 59}, {"lat": 37.533072, "lon": 122.076431, "alt": 14.8, "hr": 112, "dist": 1791.2, "speed": 1.45, "time": 2662, "temp": 26, "cadence": 59}, {"lat": 37.5331781, "lon": 122.0765239, "alt": 15.2, "hr": 110, "dist": 1806.0, "speed": 1.47, "time": 2672, "temp": 26, "cadence": 61}, {"lat": 37.5332401, "lon": 122.0765655, "alt": 15.6, "hr": 109, "dist": 1814.9, "speed": 1.47, "time": 2678, "temp": 26, "cadence": 60}, {"lat": 37.5333213, "lon": 122.0766459, "alt": 15.8, "hr": 110, "dist": 1825.2, "speed": 1.47, "time": 2685, "temp": 26, "cadence": 60}, {"lat": 37.5333404, "lon": 122.0766677, "alt": 16.0, "hr": 110, "dist": 1827.8, "speed": 1.47, "time": 2687, "temp": 26, "cadence": 60}, {"lat": 37.5333747, "lon": 122.0766961, "alt": 16.2, "hr": 113, "dist": 1833.7, "speed": 1.46, "time": 2691, "temp": 26, "cadence": 60}, {"lat": 37.5334032, "lon": 122.0767226, "alt": 16.4, "hr": 116, "dist": 1837.0, "speed": 1.45, "time": 2694, "temp": 26, "cadence": 59}, {"lat": 37.5334722, "lon": 122.0768044, "alt": 16.0, "hr": 119, "dist": 1847.2, "speed": 1.43, "time": 2701, "temp": 26, "cadence": 62}, {"lat": 37.5335184, "lon": 122.0768657, "alt": 16.2, "hr": 119, "dist": 1853.3, "speed": 1.48, "time": 2705, "temp": 26, "cadence": 62}, {"lat": 37.5335893, "lon": 122.0769711, "alt": 15.6, "hr": 116, "dist": 1866.9, "speed": 1.52, "time": 2714, "temp": 26, "cadence": 61}, {"lat": 37.5336059, "lon": 122.0769956, "alt": 15.6, "hr": 116, "dist": 1868.4, "speed": 1.49, "time": 2716, "temp": 26, "cadence": 61}, {"lat": 37.5336199, "lon": 122.07712, "alt": 15.8, "hr": 116, "dist": 1880.2, "speed": 1.56, "time": 2724, "temp": 26, "cadence": 59}, {"lat": 37.5335652, "lon": 122.0772669, "alt": 16.6, "hr": 118, "dist": 1893.7, "speed": 1.4, "time": 2733, "temp": 26, "cadence": 60}, {"lat": 37.5335523, "lon": 122.0772937, "alt": 16.8, "hr": 117, "dist": 1896.8, "speed": 1.51, "time": 2735, "temp": 26, "cadence": 60}, {"lat": 37.5335042, "lon": 122.0774119, "alt": 16.8, "hr": 118, "dist": 1908.5, "speed": 1.47, "time": 2743, "temp": 26, "cadence": 61}, {"lat": 37.5334332, "lon": 122.0775924, "alt": 17.6, "hr": 117, "dist": 1927.1, "speed": 1.47, "time": 2755, "temp": 26, "cadence": 61}, {"lat": 37.5333993, "lon": 122.0776824, "alt": 17.8, "hr": 118, "dist": 1934.4, "speed": 1.45, "time": 2761, "temp": 26, "cadence": 60}, {"lat": 37.5333619, "lon": 122.0777827, "alt": 18.6, "hr": 120, "dist": 1944.9, "speed": 1.41, "time": 2768, "temp": 26, "cadence": 61}, {"lat": 37.5333178, "lon": 122.0779137, "alt": 19.0, "hr": 122, "dist": 1957.8, "speed": 1.4, "time": 2777, "temp": 26, "cadence": 60}, {"lat": 37.5332985, "lon": 122.0779825, "alt": 19.2, "hr": 120, "dist": 1963.2, "speed": 1.4, "time": 2781, "temp": 26, "cadence": 60}, {"lat": 37.5332541, "lon": 122.0781011, "alt": 19.6, "hr": 119, "dist": 1975.6, "speed": 1.44, "time": 2789, "temp": 26, "cadence": 59}, {"lat": 37.5331896, "lon": 122.0782696, "alt": 19.8, "hr": 120, "dist": 1992.8, "speed": 1.44, "time": 2801, "temp": 26, "cadence": 59}, {"lat": 37.5331575, "lon": 122.0783353, "alt": 20.0, "hr": 119, "dist": 1999.9, "speed": 1.44, "time": 2806, "temp": 26, "cadence": 60}, {"lat": 37.5331446, "lon": 122.078363, "alt": 20.0, "hr": 119, "dist": 2002.7, "speed": 1.43, "time": 2808, "temp": 26, "cadence": 60}, {"lat": 37.5331238, "lon": 122.0784088, "alt": 20.2, "hr": 118, "dist": 2007.0, "speed": 1.42, "time": 2811, "temp": 26, "cadence": 59}, {"lat": 37.5330557, "lon": 122.0785849, "alt": 20.6, "hr": 115, "dist": 2025.0, "speed": 1.42, "time": 2823, "temp": 26, "cadence": 60}, {"lat": 37.5330298, "lon": 122.0786584, "alt": 21.2, "hr": 114, "dist": 2031.3, "speed": 1.37, "time": 2829, "temp": 26, "cadence": 59}, {"lat": 37.5330251, "lon": 122.0786712, "alt": 21.2, "hr": 114, "dist": 2032.7, "speed": 1.3, "time": 2830, "temp": 26, "cadence": 59}, {"lat": 37.5330025, "lon": 122.0787148, "alt": 22.4, "hr": 113, "dist": 2037.8, "speed": 0.63, "time": 2835, "temp": 26, "cadence": 55}, {"lat": 37.5329985, "lon": 122.0787221, "alt": 22.6, "hr": 113, "dist": 2039.0, "speed": 0.63, "time": 2836, "temp": 26, "cadence": 57}, {"lat": 37.5329772, "lon": 122.0787769, "alt": 23.4, "hr": 115, "dist": 2043.8, "speed": 0.88, "time": 2841, "temp": 26, "cadence": 58}, {"lat": 37.5329714, "lon": 122.0787979, "alt": 23.8, "hr": 117, "dist": 2046.4, "speed": 1.08, "time": 2843, "temp": 26, "cadence": 59}, {"lat": 37.5329553, "lon": 122.0788475, "alt": 24.6, "hr": 119, "dist": 2050.0, "speed": 0.96, "time": 2847, "temp": 26, "cadence": 59}, {"lat": 37.5329418, "lon": 122.0788801, "alt": 24.8, "hr": 119, "dist": 2054.6, "speed": 1.28, "time": 2850, "temp": 26, "cadence": 59}, {"lat": 37.5329146, "lon": 122.0789539, "alt": 25.6, "hr": 121, "dist": 2061.1, "speed": 1.04, "time": 2857, "temp": 26, "cadence": 57}, {"lat": 37.5328964, "lon": 122.0790017, "alt": 26.4, "hr": 124, "dist": 2065.7, "speed": 0.98, "time": 2862, "temp": 26, "cadence": 60}, {"lat": 37.5328916, "lon": 122.0790124, "alt": 26.6, "hr": 124, "dist": 2066.9, "speed": 0.98, "time": 2863, "temp": 26, "cadence": 60}, {"lat": 37.5328873, "lon": 122.079022, "alt": 26.8, "hr": 125, "dist": 2067.9, "speed": 0.93, "time": 2864, "temp": 26, "cadence": 59}, {"lat": 37.5328702, "lon": 122.0790615, "alt": 27.6, "hr": 126, "dist": 2071.8, "speed": 0.92, "time": 2868, "temp": 26, "cadence": 54}, {"lat": 37.5328611, "lon": 122.07909, "alt": 28.0, "hr": 128, "dist": 2074.7, "speed": 1.01, "time": 2871, "temp": 26, "cadence": 61}, {"lat": 37.5328449, "lon": 122.0791285, "alt": 28.8, "hr": 129, "dist": 2078.8, "speed": 0.95, "time": 2875, "temp": 26, "cadence": 61}, {"lat": 37.532833, "lon": 122.0791579, "alt": 29.4, "hr": 131, "dist": 2081.5, "speed": 1.07, "time": 2878, "temp": 26, "cadence": 56}, {"lat": 37.5328201, "lon": 122.0791864, "alt": 29.8, "hr": 133, "dist": 2085.0, "speed": 1.02, "time": 2881, "temp": 26, "cadence": 61}, {"lat": 37.532805, "lon": 122.0792288, "alt": 30.4, "hr": 136, "dist": 2088.2, "speed": 0.91, "time": 2885, "temp": 26, "cadence": 59}, {"lat": 37.5327939, "lon": 122.0792599, "alt": 30.8, "hr": 138, "dist": 2090.7, "speed": 0.94, "time": 2888, "temp": 26, "cadence": 57}, {"lat": 37.5327783, "lon": 122.0793014, "alt": 31.2, "hr": 139, "dist": 2095.6, "speed": 0.94, "time": 2892, "temp": 26, "cadence": 61}, {"lat": 37.5327641, "lon": 122.0793342, "alt": 32.0, "hr": 141, "dist": 2098.3, "speed": 0.89, "time": 2895, "temp": 26, "cadence": 53}, {"lat": 37.5327459, "lon": 122.0793783, "alt": 33.0, "hr": 143, "dist": 2102.7, "speed": 1.28, "time": 2899, "temp": 26, "cadence": 56}, {"lat": 37.5327412, "lon": 122.0793902, "alt": 33.0, "hr": 142, "dist": 2103.7, "speed": 0.98, "time": 2900, "temp": 26, "cadence": 57}, {"lat": 37.5326927, "lon": 122.0795065, "alt": 33.0, "hr": 142, "dist": 2116.3, "speed": 1.38, "time": 2909, "temp": 26, "cadence": 59}, {"lat": 37.5326253, "lon": 122.0796928, "alt": 33.0, "hr": 144, "dist": 2134.0, "speed": 1.37, "time": 2922, "temp": 26, "cadence": 59}, {"lat": 37.5325775, "lon": 122.0798578, "alt": 32.8, "hr": 143, "dist": 2150.3, "speed": 1.44, "time": 2933, "temp": 26, "cadence": 60}, {"lat": 37.5325321, "lon": 122.0799615, "alt": 32.8, "hr": 141, "dist": 2160.0, "speed": 1.42, "time": 2940, "temp": 26, "cadence": 60}, {"lat": 37.5324908, "lon": 122.0800735, "alt": 32.8, "hr": 138, "dist": 2171.7, "speed": 1.44, "time": 2948, "temp": 26, "cadence": 59}, {"lat": 37.5324778, "lon": 122.0800981, "alt": 32.8, "hr": 137, "dist": 2175.1, "speed": 1.43, "time": 2950, "temp": 26, "cadence": 59}, {"lat": 37.5324564, "lon": 122.0801368, "alt": 33.0, "hr": 134, "dist": 2179.1, "speed": 1.42, "time": 2954, "temp": 26, "cadence": 60}, {"lat": 37.5324449, "lon": 122.080156, "alt": 33.4, "hr": 133, "dist": 2181.1, "speed": 1.39, "time": 2956, "temp": 26, "cadence": 60}, {"lat": 37.5324326, "lon": 122.0801769, "alt": 34.2, "hr": 132, "dist": 2183.9, "speed": 1.13, "time": 2959, "temp": 26, "cadence": 61}, {"lat": 37.5324243, "lon": 122.0802166, "alt": 35.4, "hr": 130, "dist": 2187.2, "speed": 0.63, "time": 2963, "temp": 26, "cadence": 59}, {"lat": 37.5324371, "lon": 122.0803299, "alt": 35.8, "hr": 134, "dist": 2197.6, "speed": 1.32, "time": 2970, "temp": 26, "cadence": 60}, {"lat": 37.5324399, "lon": 122.0803466, "alt": 35.6, "hr": 134, "dist": 2199.1, "speed": 1.32, "time": 2971, "temp": 26, "cadence": 61}, {"lat": 37.5324564, "lon": 122.0804008, "alt": 35.6, "hr": 137, "dist": 2204.1, "speed": 1.44, "time": 2975, "temp": 26, "cadence": 62}, {"lat": 37.5324922, "lon": 122.0804426, "alt": 36.2, "hr": 138, "dist": 2209.1, "speed": 1.37, "time": 2979, "temp": 26, "cadence": 59}, {"lat": 37.5325097, "lon": 122.0805444, "alt": 36.0, "hr": 137, "dist": 2218.6, "speed": 1.41, "time": 2985, "temp": 26, "cadence": 59}, {"lat": 37.5324963, "lon": 122.0805738, "alt": 36.4, "hr": 134, "dist": 2221.6, "speed": 1.46, "time": 2987, "temp": 26, "cadence": 59}, {"lat": 37.5324712, "lon": 122.0806122, "alt": 36.8, "hr": 131, "dist": 2225.5, "speed": 1.46, "time": 2990, "temp": 26, "cadence": 56}, {"lat": 37.5324532, "lon": 122.0806349, "alt": 36.8, "hr": 131, "dist": 2228.8, "speed": 1.42, "time": 2992, "temp": 26, "cadence": 58}, {"lat": 37.5323673, "lon": 122.0807609, "alt": 37.2, "hr": 128, "dist": 2242.6, "speed": 1.42, "time": 3002, "temp": 26, "cadence": 59}, {"lat": 37.5323484, "lon": 122.0807874, "alt": 37.2, "hr": 128, "dist": 2245.7, "speed": 1.38, "time": 3004, "temp": 26, "cadence": 59}, {"lat": 37.532321, "lon": 122.0808311, "alt": 37.4, "hr": 128, "dist": 2251.8, "speed": 1.42, "time": 3008, "temp": 26, "cadence": 59}, {"lat": 37.5322845, "lon": 122.0808911, "alt": 37.6, "hr": 127, "dist": 2259.5, "speed": 1.42, "time": 3013, "temp": 26, "cadence": 60}, {"lat": 37.5322203, "lon": 122.0809839, "alt": 37.8, "hr": 126, "dist": 2270.5, "speed": 1.44, "time": 3021, "temp": 26, "cadence": 61}, {"lat": 37.5321665, "lon": 122.081057, "alt": 38.2, "hr": 124, "dist": 2279.7, "speed": 1.44, "time": 3027, "temp": 26, "cadence": 60}, {"lat": 37.5320726, "lon": 122.0811826, "alt": 38.0, "hr": 121, "dist": 2295.2, "speed": 1.47, "time": 3037, "temp": 26, "cadence": 61}, {"lat": 37.5320644, "lon": 122.081197, "alt": 38.0, "hr": 121, "dist": 2296.9, "speed": 1.48, "time": 3038, "temp": 26, "cadence": 61}, {"lat": 37.5319573, "lon": 122.0813548, "alt": 38.4, "hr": 119, "dist": 2312.6, "speed": 1.47, "time": 3049, "temp": 26, "cadence": 60}, {"lat": 37.5319319, "lon": 122.0813631, "alt": 38.4, "hr": 118, "dist": 2315.5, "speed": 1.47, "time": 3051, "temp": 26, "cadence": 60}, {"lat": 37.5318811, "lon": 122.0813517, "alt": 39.4, "hr": 117, "dist": 2320.6, "speed": 1.46, "time": 3055, "temp": 26, "cadence": 57}, {"lat": 37.531866, "lon": 122.0813497, "alt": 39.6, "hr": 117, "dist": 2322.0, "speed": 1.45, "time": 3056, "temp": 26, "cadence": 57}, {"lat": 37.5317815, "lon": 122.0813162, "alt": 39.4, "hr": 120, "dist": 2330.4, "speed": 1.43, "time": 3062, "temp": 26, "cadence": 62}, {"lat": 37.5317509, "lon": 122.0812927, "alt": 39.4, "hr": 121, "dist": 2334.0, "speed": 1.43, "time": 3064, "temp": 26, "cadence": 61}, {"lat": 37.5316869, "lon": 122.0812755, "alt": 39.8, "hr": 124, "dist": 2340.7, "speed": 1.44, "time": 3069, "temp": 26, "cadence": 61}, {"lat": 37.5316631, "lon": 122.081289, "alt": 40.0, "hr": 125, "dist": 2344.6, "speed": 1.44, "time": 3072, "temp": 26, "cadence": 61}, {"lat": 37.531587, "lon": 122.0813631, "alt": 40.6, "hr": 127, "dist": 2356.4, "speed": 1.41, "time": 3081, "temp": 26, "cadence": 61}, {"lat": 37.5314742, "lon": 122.081499, "alt": 40.8, "hr": 124, "dist": 2373.6, "speed": 1.4, "time": 3093, "temp": 26, "cadence": 59}, {"lat": 37.5314445, "lon": 122.0815139, "alt": 40.8, "hr": 125, "dist": 2380.3, "speed": 1.39, "time": 3099, "temp": 26, "cadence": 56}], "laps": [{"dist": 1000.0, "time": 741.3, "avg_hr": 102, "max_hr": 113, "avg_speed": 1.35, "ascent": 3, "descent": 38}, {"dist": 1000.0, "time": 2065.0, "avg_hr": 92, "max_hr": 122, "avg_speed": 0.48, "ascent": 14, "descent": 4}, {"dist": 380.3, "time": 292.7, "avg_hr": 129, "max_hr": 144, "avg_speed": 1.3, "ascent": 21, "descent": 0}]}